geodiff/__init__.py
geodiff/aux_nets.py
geodiff/cst.py
geodiff/hicks_henne.py
geodiff/loss_functions/chamfer.py
geodiff/monotonic_nets/__init__.py
geodiff/monotonic_nets/min_max_net.py
geodiff/monotonic_nets/smooth_min_max_net.py
geodiff/neural_ode.py
geodiff/nice.py
geodiff/nig_net.py
geodiff/real_nvp.py
geodiff/sampling.py
geodiff/template_architectures.py
geodiff/transforms.py
geodiff/utils.py
geodiff-0.9.4.dist-info/licenses/LICENSE
geodiff-0.9.4.dist-info/WHEEL
geodiff-0.9.4.dist-info/METADATA
geodiff-0.9.4.dist-info/RECORD
