Metadata-Version: 2.4
Name: geodiff
Version: 0.9.4
Summary: Differentiable geometry representations for shape parameterization and optimization.
Keywords: differentiable-geometry,shape-optimization,PyTorch,machine-learning,deep-learning,geometric-deep-learning,CFD,design-optimization
Author: Atharva Aalok
Author-email: Atharva Aalok <atharvaaalok@gmail.com>
License-Expression: MIT
License-File: LICENSE
Classifier: Development Status :: 1 - Planning
Classifier: Intended Audience :: Developers
Classifier: Intended Audience :: Education
Classifier: Intended Audience :: Science/Research
Classifier: License :: OSI Approved :: MIT License
Classifier: Operating System :: OS Independent
Classifier: Programming Language :: Python :: 3
Classifier: Programming Language :: Python :: 3.12
Classifier: Programming Language :: Python :: 3.13
Classifier: Topic :: Scientific/Engineering
Classifier: Topic :: Scientific/Engineering :: Artificial Intelligence
Classifier: Topic :: Scientific/Engineering :: Mathematics
Classifier: Topic :: Software Development
Classifier: Topic :: Software Development :: Libraries
Classifier: Topic :: Software Development :: Libraries :: Python Modules
Requires-Dist: matplotlib>=3.10.6
Requires-Dist: numpy>=2.3.3
Requires-Dist: torch>=2.8.0
Requires-Dist: torchdiffeq>=0.2.5
Maintainer: Atharva Aalok
Maintainer-email: Atharva Aalok <atharvaaalok@gmail.com>
Requires-Python: >=3.12.0
Project-URL: bugtracker, https://github.com/atharvaaalok/geodiff/issues
Project-URL: changelog, https://github.com/atharvaaalok/geodiff/blob/main/CHANGELOG.md
Project-URL: documentation, https://atharvaaalok.github.io/geodiff/
Project-URL: forum, https://github.com/atharvaaalok/geodiff/discussions
Project-URL: homepage, https://atharvaaalok.github.io/geodiff/
Project-URL: repository, https://github.com/atharvaaalok/geodiff
